Workbook

Sheet VENDOR MASTER
A1: Vendor_ID | B1: Vendor_Name | C1: GST_Number | D1: Payment_Terms | E1: Bank_Name | F1: Account_Number | G1: Status | H1: Vendor Name | I1: Sum of Spend Amount
A2: V001 | B2: Sri Lakshmi Metals | C2: 33ABCDE1234F1Z5 | D2: 30 Days | E2: SBI | F2: 1234567890 | G2: Active | H2: Vendor A | I2: 150000
A3: V002 | B3: Kaveri Traders | C3: 33PQRS5678L1Z2 | D3: 45 Days | E3: HDFC | F3: 2345678901 | G3: Active | H3: Vendor B | I3: 75000
A4: V003 | B4: Vinayaga Services | C4: 33LMNOP4321Q1Z9 | D4: 15 Days | E4: ICICI | F4: 3456789012 | G4: Active | H4: Vendor C | I4: 45000
A5: V004 | B5: TMT Rod | C5: 33LMNOP4556Q1Z0 | D5: 25 Days | E5: CUB | F5: 98562314 | G5: Active | H5: Vendor D | I5: 25000
A6: V005 | B6: Hyder Sweets | C6: 33LMNOP12341Q1Z8 | D6: 60 Days | E6: IB | F6: 258741369 | G6: Active | H6: Vendor E | I6: 35000
A7: Payment_Terms | B7: (All)
A9: Sum of Sum of Spend Amount | B9: Column Labels
A10: Row Labels | B10: CUB | C10: HDFC | D10: IB | E10: ICICI | F10: SBI | G10: Grand Total
A11: Hyder Sweets | D11: 35000 | G11: 35000
A12: Kaveri Traders | C12: 75000 | G12: 75000
A13: Sri Lakshmi Metals | F13: 150000 | G13: 150000
A14: TMT Rod | B14: 25000 | G14: 25000
A15: Vinayaga Services | E15: 45000 | G15: 45000
A16: Grand Total | B16: 25000 | C16: 75000 | D16: 35000 | E16: 45000 | F16: 150000 | G16: 330000

Sheet PURCHASE REQUISITION
A1: PR_No | B1: Date | C1: Dept | D1: Item | E1: Qty | F1: Est_Price | G1: Total | H1: Status
A2: PR001 | B2: 45992 | C2: Stores | D2: Printer | E2: 2 | F2: 12000 | G2: =F2*E2 -> 24000 | H2: =IF(G2>F2,"Approved","Rejected") -> Approved
A3: PR002 | B3: 45993 | C3: Stores | D3: Moniter | E3: 2 | F3: 15000 | G3: =F3*E3 -> 30000 | H3: =IF(G3>F3,"Approved","Rejected") -> Approved
A4: PR003 | B4: 45994 | C4: Stores | D4: Mouse | E4: 2 | F4: 700 | G4: =F4*E4 -> 1400 | H4: =IF(G4>F4,"Approved","Rejected") -> Approved
A5: PR004 | B5: 45995 | C5: Stores | D5: CPU | E5: 2 | F5: 8000 | G5: =F5*E5 -> 16000 | H5: =IF(G5>F5,"Approved","Rejected") -> Approved
A6: PR005 | B6: 45996 | C6: Stores | D6: Keyboard | E6: 2 | F6: 800 | G6: =F6*E6 -> 1600 | H6: =IF(G6>F6,"Approved","Rejected") -> Approved

Sheet PURCHASE ORDER 
A1: PO_No | B1: PR_No | C1: Vendor_ID | D1: PO_Date | E1: Item | F1: Qty | G1: Rate | H1: PO_Value | I1: Status
A2: PO101 | B2: PR001 | C2: V001 | D2: 45994 | E2: Printer | F2: 2 | G2: 11500 | H2: =G2*F2 -> 23000 | I2: =IF(H2>0,"Open","Close") -> Open
A3: PO102 | B3: PR002 | C3: V002 | D3: 45995 | E3: CPU | F3: 5 | G3: 8000 | H3: =G3*F3 -> 40000 | I3: =IF(H3>0,"Open","Close") -> Open
A4: PO103 | B4: PR003 | C4: V003 | D4: 45996 | E4: Keyboard | F4: 3 | G4: 600 | H4: =G4*F4 -> 1800 | I4: =IF(H4>0,"Open","Close") -> Open
A5: PO104 | B5: PR004 | C5: V004 | D5: 45997 | E5: Scanner | F5: 2 | G5: 7800 | H5: =G5*F5 -> 15600 | I5: =IF(H5>0,"Open","Close") -> Open
A6: PO105 | B6: PR005 | C6: V005 | D6: 45998 | E6: Gaming Laptop | F6: 3 | G6: 67000 | H6: =G6*F6 -> 201000 | I6: =IF(H6>0,"Open","Close") -> Open

Sheet GOODS RECEIPT NOTE(GRN)
A1: GRN_No | B1: PO_No | C1: Accepted Qty | D1: Received_Qty | E1: Received_Date | F1: Quality_Status
A2: GRN501 | B2: PO101 | C2: 5 | D2: 2 | E2: 45997 | F2: =IF(C2=D2,"Accepted",IF(C2>0,"Partial Accepted","Rejected")) -> Partial Accepted
A3: GRN502 | B3: PO102 | C3: 1 | D3: 1 | E3: 45998 | F3: =IF(C3=D3,"Accepted",IF(C3>0,"Partial Accepted","Rejected")) -> Accepted
A4: GRN503 | B4: PO103 | C4: 2 | D4: 2 | E4: 45999 | F4: =IF(C4=D4,"Accepted",IF(C4>0,"Partial Accepted","Rejected")) -> Accepted
A5: GRN504 | B5: PO104 | C5: 3 | D5: 3 | E5: 46000 | F5: =IF(C5=D5,"Accepted",IF(C5>0,"Partial Accepted","Rejected")) -> Accepted

Sheet PAYMENT TRACKER
A1: Payment_ID | B1: Invoice_No | C1: Vendor_ID | D1: Due_Date | E1: Amount | F1: Payment_Status
A2: PAY3001 | B2: INV9001 | C2: V001 | D2: 46027 | E2: 23000 | F2: =IF(E2>0,"pending","paid") -> pending
A3: PAY3002 | B3: INV9002 | C3: V002 | D3: 46028 | E3: 25000 | F3: =IF(E3>0,"pending","paid") -> pending
A4: PAY3003 | B4: INV9003 | C4: V003 | D4: 46029 | E4: 78000 | F4: =IF(E4>0,"pending","paid") -> pending
A5: PAY3004 | B5: INV9004 | C5: V004 | D5: 46030 | E5: 450120 | F5: =IF(E5>0,"pending","paid") -> pending
A6: PAY3005 | B6: INV9005 | C6: V005 | D6: 46031 | E6: 5785 | F6: =IF(E6>0,"pending","paid") -> pending
A13: Due_Date | B13: (All)
A14: Payment_Status | B14: (All)
A16: Row Labels | B16: Sum of Amount
A17: V001 | B17: 23000
A18: V002 | B18: 25000
A19: V003 | B19: 78000
A20: V004 | B20: 450120
A21: V005 | B21: 5785
A22: Grand Total | B22: 581905

Sheet INVOICE REGISTER
A1: Invoice_No | B1: Vendor_ID | C1: PO_No | D1: GRN_No | E1: Invoice_Amount | F1: Match_Status
A2: INV9001 | B2: V001 | C2: PO101 | D2: GRN501 | E2: 23000 | F2: =IFERROR(IF(VLOOKUP(C2,'INVOICE REGISTER'!A:H,8,FALSE)=E2,"Matched","Blocked"),"Blocked") -> Blocked
A3: INV9002 | B3: V002 | C3: PO102 | D3: GRN502 | E3: 50000 | F3: =IFERROR(IF(VLOOKUP(C3,'INVOICE REGISTER'!A:H,8,FALSE)=E3,"Matched","Blocked"),"Blocked") -> Blocked
A4: INV9003 | B4: V003 | C4: PO103 | D4: GRN503 | E4: 55000 | F4: =IFERROR(IF(VLOOKUP(C4,'INVOICE REGISTER'!A:H,8,FALSE)=E4,"Matched","Blocked"),"Blocked") -> Blocked
A5: INV9004 | B5: V004 | C5: PO104 | D5: GRN504 | E5: 58000 | F5: =IFERROR(IF(VLOOKUP(C5,'INVOICE REGISTER'!A:H,8,FALSE)=E5,"Matched","Blocked"),"Blocked") -> Blocked
A6: INV9005 | B6: V005 | C6: PO105 | D6: GRN505 | E6: 45000 | F6: =IFERROR(IF(VLOOKUP(C6,'INVOICE REGISTER'!A:H,8,FALSE)=E6,"Matched","Blocked"),"Blocked") -> Blocked

Sheet DASHBOARDS
